Metadata-Version: 1.1
Name: simplestorage
Version: 0.2.2
Summary: Storage client for local and gcloud
Home-page: https://github.com/tbchk/simple-storage
Author: Juan F. Hernandez
Author-email: jhernandez426@gmail.com
License: MIT
Download-URL: https://github.com/tbchk/simple-storage/archive/v0.2.2.tar.gz
Keywords: google,cloud,storage,local
Platform: UNKNOWN
